{
  "produtoLista": [
    {
      "produtoNome": "Caju",
      "categoria": "Frutas",
      "qualidade": "Novo",
      "preco": 25,
      "descricao": "Caju fresquinho",
      "data": "2023-02-03T03:00:00.000Z",
      "id": 1
    },
    {
      "produtoNome": "Banana",
      "categoria": "Frutas",
      "qualidade": "Novo",
      "preco": 16,
      "descricao": "Banana nanica",
      "data": "2023-02-03T03:00:00.000Z",
      "id": 2
    },
    {
      "produtoNome": "Abacate",
      "categoria": "Frutas",
      "qualidade": "Usado",
      "preco": 8,
      "descricao": "Abacate não fresco",
      "data": "2023-02-03T03:00:00.000Z",
      "id": 3
    },
    {
      "produtoNome": "Manga",
      "categoria": "Frutas",
      "qualidade": "Novo",
      "preco": 8.99,
      "descricao": "Manga fresca do Brasil",
      "data": "2023-02-03T03:00:00.000Z",
      "id": 4
    }
  ],
  "comments": [
    {
      "id": 1,
      "body": "some comment",
      "postId": 1
    }
  ],
  "profile": {
    "name": "typicode"
  }
}